datasette_search_all/__init__.py
datasette_search_all/utils.py
datasette_search_all/templates/index.html
datasette_search_all/templates/search_all.html
datasette_search_all-1.1.4.dist-info/LICENSE
datasette_search_all-1.1.4.dist-info/METADATA
datasette_search_all-1.1.4.dist-info/WHEEL
datasette_search_all-1.1.4.dist-info/entry_points.txt
datasette_search_all-1.1.4.dist-info/top_level.txt
datasette_search_all-1.1.4.dist-info/RECORD
