Metadata-Version: 2.1
Name: datasette-search-all
Version: 1.1.4
Summary: Datasette plugin for searching all searchable tables at once
Home-page: https://github.com/simonw/datasette-search-all
Author: Simon Willison
License: Apache License, Version 2.0
Project-URL: Issues, https://github.com/simonw/datasette-search-all/issues
Project-URL: CI, https://github.com/simonw/datasette-search-all/actions
Project-URL: Changelog, https://github.com/simonw/datasette-search-all/releases
Requires-Python: >=3.7
License-File: LICENSE
Requires-Dist: datasette >=0.63.1
Provides-Extra: playwright
Requires-Dist: pytest-playwright ; extra == 'playwright'
Provides-Extra: test
Requires-Dist: pytest ; extra == 'test'
Requires-Dist: pytest-asyncio ; extra == 'test'
Requires-Dist: sqlite-utils ; extra == 'test'
Requires-Dist: nest-asyncio ; extra == 'test'
